Verilog/test/alu.sv
typedef enum logic [1:0] {
  add = 2'h1,
  sub = 2'h2,
  nop = 2'h0
} operation_t /*verilator public*/;

module alu #(
    parameter WIDTH = 8
) (
    input clk,
    input rst,

    input operation_t op_in,
    input [WIDTH-1:0] a_in,
    input [WIDTH-1:0] b_in,
    input in_valid,

    output logic [WIDTH-1:0] out,
    output logic out_valid
);

  operation_t op_in_r;
  logic [WIDTH-1:0] a_in_r;
  logic [WIDTH-1:0] b_in_r;
  logic in_valid_r;
  logic [WIDTH-1:0] result;

  always_ff @(posedge clk, posedge rst) begin
    if (rst) begin
      op_in_r <= nop;
      a_in_r <= '0;
      b_in_r <= '0;
      in_valid_r <= '0;
    end else begin
      op_in_r <= op_in;
      a_in_r <= a_in;
      b_in_r <= b_in;
      in_valid_r <= in_valid;
    end
  end

  always_comb begin
    result = '0;
    if (in_valid_r) begin
      case (op_in_r)
        add: result = a_in_r + b_in_r;
        sub: result = a_in_r + (~b_in_r + 1'b1);
        default: result = '0;
      endcase
    end
  end

  always_ff @(posedge clk, posedge rst) begin
    if (rst) begin
      out <= '0;
      out_valid <= '0;
    end else begin
      out <= result;
      out_valid <= in_valid_r;
    end
  end
endmodule

Verilog/test/waveform.vcd
$version Generated by VerilatedVcd $end
$timescale 1ps $end

 $scope module TOP $end
  $var wire  8 + a_in [7:0] $end
  $var wire  8 , b_in [7:0] $end
  $var wire  1 ( clk $end
  $var wire  1 - in_valid $end
  $var wire  2 * op_in [1:0] $end
  $var wire  8 . out [7:0] $end
  $var wire  1 / out_valid $end
  $var wire  1 ) rst $end
  $scope module alu $end
   $var wire 32 0 WIDTH [31:0] $end
   $var wire  8 + a_in [7:0] $end
   $var wire  8 $ a_in_r [7:0] $end
   $var wire  8 , b_in [7:0] $end
   $var wire  8 % b_in_r [7:0] $end
   $var wire  1 ( clk $end
   $var wire  1 - in_valid $end
   $var wire  1 & in_valid_r $end
   $var wire  2 * op_in [1:0] $end
   $var wire  2 # op_in_r [1:0] $end
   $var wire  8 . out [7:0] $end
   $var wire  1 / out_valid $end
   $var wire  8 ' result [7:0] $end
   $var wire  1 ) rst $end
  $upscope $end
 $upscope $end
$enddefinitions $end


#0
b11 #
b01010011 $
b00100001 %
1&
b00000000 '
1(
0)
b00 *
b11100100 +
b01111000 ,
0-
b10110110 .
0/
b00000000000000000000000000001000 0
#1
0(
#2
b00 #
b11100100 $
b01111000 %
0&
1(
b00000000 .
1/
#3
b00000000 $
b00000000 %
0(
1)
b00000000 +
b00000000 ,
0/
#4
1(
#5
0(
#6
1(
0)
#7
0(
#8
1(
#9
0(
#10
1(
#11
0(
#12
1(
b01 *
b00011001 +
b01110100 ,
1-
#13
0(
#14
b01 #
b00011001 $
b01110100 %
1&
b10001101 '
1(
b00 *
0-
#15
0(
#16
b00 #
0&
b00000000 '
1(
b10001101 .
1/
#17
0(
#18
1(
b00000000 .
0/
#19
0(
#20
1(
b10 *
b10101001 +
b01111101 ,
1-
#21
0(
#22
b10 #
b10101001 $
b01111101 %
1&
b00101100 '
1(
b00 *
0-
#23
0(
#24
b00 #
0&
b00000000 '
1(
b00101100 .
1/
#25
0(
#26
1(
b00000000 .
0/
#27
0(
#28
1(
b01 *
b01111110 +
b11111100 ,
1-
#29
0(
#30
b01 #
b01111110 $
b11111100 %
1&
b01111010 '
1(
b00 *
0-
#31
0(
#32
b00 #
0&
b00000000 '
1(
b01111010 .
1/
#33
0(
#34
1(
b00000000 .
0/
#35
0(
#36
1(
b10 *
b11010010 +
b00001100 ,
1-
#37
0(
#38
b10 #
b11010010 $
b00001100 %
1&
b11000110 '
1(
b00 *
0-
#39
0(
#40
b00 #
0&
b00000000 '
1(
b11000110 .
1/
#41
0(
#42
1(
b00000000 .
0/
#43
0(
#44
1(
b01 *
b00000010 +
b00110001 ,
1-
#45
0(
#46
b01 #
b00000010 $
b00110001 %
1&
b00110011 '
1(
b00 *
0-
#47
0(
#48
b00 #
0&
b00000000 '
1(
b00110011 .
1/
#49
0(
#50
1(
b00000000 .
0/
#51
0(
#52
1(
b10 *
b00001000 +
b01111001 ,
1-
#53
0(
#54
b10 #
b00001000 $
b01111001 %
1&
b10001111 '
1(
b00 *
0-
#55
0(
#56
b00 #
0&
b00000000 '
1(
b10001111 .
1/
#57
0(
#58
1(
b00000000 .
0/
#59
0(
#60
1(
b01 *
b01111101 +
b10000011 ,
1-
#61
0(
#62
b01 #
b01111101 $
b10000011 %
1&
1(
b00 *
0-
#63
0(
#64
b00 #
0&
1(
1/
#65
0(
#66
1(
0/
#67
0(
#68
1(
b10 *
b01111011 +
b11010101 ,
1-
#69
0(
#70
b10 #
b01111011 $
b11010101 %
1&
b10100110 '
1(
b00 *
0-
#71
0(
#72
b00 #
0&
b00000000 '
1(
b10100110 .
1/
#73
0(
#74
1(
b00000000 .
0/
#75
0(
#76
1(
b01 *
b11101101 +
b11000111 ,
1-
#77
0(
#78
b01 #
b11101101 $
b11000111 %
1&
b10110100 '
1(
b00 *
0-
#79
0(
#80
b00 #
0&
b00000000 '
1(
b10110100 .
1/
#81
0(
#82
1(
b00000000 .
0/
#83
0(
#84
1(
b10 *
b00111011 +
b10110101 ,
1-
#85
0(
#86
b10 #
b00111011 $
b10110101 %
1&
b10000110 '
1(
b00 *
0-
#87
0(
#88
b00 #
0&
b00000000 '
1(
b10000110 .
1/
#89
0(
#90
1(
b00000000 .
0/
#91
0(
#92
1(
b01 *
b10011001 +
b10101001 ,
1-
#93
0(
#94
b01 #
b10011001 $
b10101001 %
1&
b01000010 '
1(
b00 *
0-
#95
0(
#96
b00 #
0&
b00000000 '
1(
b01000010 .
1/
#97
0(
#98
1(
b00000000 .
0/
#99
0(
#100
1(
b10 *
b11001010 +
b01001100 ,
1-
#101
0(
#102
b10 #
b11001010 $
b01001100 %
1&
b01111110 '
1(
b00 *
0-
#103
0(
#104
b00 #
0&
b00000000 '
1(
b01111110 .
1/
#105
0(
#106
1(
b00000000 .
0/
#107
0(
#108
1(
b01 *
b11001000 +
b10100110 ,
1-
#109
0(
#110
b01 #
b11001000 $
b10100110 %
1&
b01101110 '
1(
b00 *
0-
#111
0(
#112
b00 #
0&
b00000000 '
1(
b01101110 .
1/
#113
0(
#114
1(
b00000000 .
0/
#115
0(
#116
1(
b10 *
b01010101 +
b01100000 ,
1-
#117
0(
#118
b10 #
b01010101 $
b01100000 %
1&
b11110101 '
1(
b00 *
0-
#119
0(
#120
b00 #
0&
b00000000 '
1(
b11110101 .
1/
#121
0(
#122
1(
b00000000 .
0/
#123
0(
#124
1(
b01 *
b11101101 +
b10101100 ,
1-
#125
0(
#126
b01 #
b11101101 $
b10101100 %
1&
b10011001 '
1(
b00 *
0-
#127
0(
#128
b00 #
0&
b00000000 '
1(
b10011001 .
1/
#129
0(
#130
1(
b00000000 .
0/
#131
0(
#132
1(
b10 *
b10110101 +
b00000111 ,
1-
#133
0(
#134
b10 #
b10110101 $
b00000111 %
1&
b10101110 '
1(
b00 *
0-
#135
0(
#136
b00 #
0&
b00000000 '
1(
b10101110 .
1/
#137
0(
#138
1(
b00000000 .
0/
#139
0(
#140
1(
b01 *
b00100001 +
b01011110 ,
1-
#141
0(
#142
b01 #
b00100001 $
b01011110 %
1&
b01111111 '
1(
b00 *
0-
#143
0(
#144
b00 #
0&
b00000000 '
1(
b01111111 .
1/
#145
0(
#146
1(
b00000000 .
0/
#147
0(
#148
1(
b10 *
b10000100 +
b10011111 ,
1-
#149
0(
#150
b10 #
b10000100 $
b10011111 %
1&
b11100101 '
1(
b00 *
0-
#151
0(
#152
b00 #
0&
b00000000 '
1(
b11100101 .
1/
#153
0(
#154
1(
b00000000 .
0/
#155
0(
#156
1(
b01 *
b01011010 +
b01010111 ,
1-
#157
0(
#158
b01 #
b01011010 $
b01010111 %
1&
b10110001 '
1(
b00 *
0-
#159
0(
#160
b00 #
0&
b00000000 '
1(
b10110001 .
1/
#161
0(
#162
1(
b00000000 .
0/
#163
0(
#164
1(
b10 *
b10101100 +
b01011101 ,
1-
#165
0(
#166
b10 #
b10101100 $
b01011101 %
1&
b01001111 '
1(
b00 *
0-
#167
0(
#168
b00 #
0&
b00000000 '
1(
b01001111 .
1/
#169
0(
#170
1(
b00000000 .
0/
#171
0(
#172
1(
b01 *
b10001000 +
b10110100 ,
1-
#173
0(
#174
b01 #
b10001000 $
b10110100 %
1&
b00111100 '
1(
b00 *
0-
#175
0(
#176
b00 #
0&
b00000000 '
1(
b00111100 .
1/
#177
0(
#178
1(
b00000000 .
0/
#179
0(
#180
1(
b10 *
b11010110 +
b00000110 ,
1-
#181
0(
#182
b10 #
b11010110 $
b00000110 %
1&
b11010000 '
1(
b00 *
0-
#183
0(
#184
b00 #
0&
b00000000 '
1(
b11010000 .
1/
#185
0(
#186
1(
b00000000 .
0/
#187
0(
#188
1(
b01 *
b00111000 +
b01010001 ,
1-
#189
0(
#190
b01 #
b00111000 $
b01010001 %
1&
b10001001 '
1(
b00 *
0-
#191
0(
#192
b00 #
0&
b00000000 '
1(
b10001001 .
1/
#193
0(
#194
1(
b00000000 .
0/
#195
0(
#196
1(
b10 *
b11011011 +
b00100101 ,
1-
#197
0(
#198
b10 #
b11011011 $
b00100101 %
1&
b10110110 '
1(
b00 *
0-
